buffr/__init__.py
buffr/buffers.py
buffr-0.0.3.dist-info/METADATA
buffr-0.0.3.dist-info/WHEEL
buffr-0.0.3.dist-info/top_level.txt
buffr-0.0.3.dist-info/RECORD
